cgreedy/LICENSE.md
cgreedy/README.md
cgreedy/__init__.py
cgreedy/alg.py
cgreedy/linux_arm64/libcgreedy.so
cgreedy/linux_x86/libcgreedy.so
cgreedy/mac_arm64/libcgreedy.dylib
cgreedy/mac_x86/libcgreedy.dylib
cgreedy/windows_x86/libcgreedy.dll
cgreedy-0.0.4.dist-info/METADATA
cgreedy-0.0.4.dist-info/WHEEL
cgreedy-0.0.4.dist-info/top_level.txt
cgreedy-0.0.4.dist-info/RECORD
