Metadata-Version: 2.4
Name: cgreedy
Version: 0.0.4
Summary: A greedy algorithm using multiple cost functions for finding efficient contraction paths
Author: Mark Blacher and Sheela Orgler
License: MIT
Classifier: License :: OSI Approved :: MIT License
Classifier: Programming Language :: Python :: 3
Requires-Dist: numpy
Dynamic: author
Dynamic: classifier
Dynamic: description
Dynamic: description-content-type
Dynamic: license
Dynamic: requires-dist
Dynamic: summary
